[{"_path":"/adobe-pdf-library/dot-net/getting-started","_dir":"dot-net","_draft":false,"_partial":false,"_locale":"","title":"Getting Started","description":"Adobe PDF Library .NET","icon":"ri:walk-fill","_type":"markdown","_id":"content:1.adobe-pdf-library:4.dot-net:1.getting-started.md","_source":"content","_file":"1.adobe-pdf-library/4.dot-net/1.getting-started.md","_stem":"1.adobe-pdf-library/4.dot-net/1.getting-started","_extension":"md"},{"_path":"/adobe-pdf-library/dot-net/firewall-issues","_dir":"dot-net","_draft":false,"_partial":false,"_locale":"","title":"Firewall Issues","description":"Adobe PDF Library .NET","icon":"mdi:hand-clap","_type":"markdown","_id":"content:1.adobe-pdf-library:4.dot-net:3.firewall-issues.md","_source":"content","_file":"1.adobe-pdf-library/4.dot-net/3.firewall-issues.md","_stem":"1.adobe-pdf-library/4.dot-net/3.firewall-issues","_extension":"md"}]